google/_async_resumable_media/__init__.py
google/_async_resumable_media/_download.py
google/_async_resumable_media/_helpers.py
google/_async_resumable_media/_upload.py
google/_async_resumable_media/requests/__init__.py
google/_async_resumable_media/requests/_request_helpers.py
google/_async_resumable_media/requests/download.py
google/_async_resumable_media/requests/upload.py
google/resumable_media/__init__.py
google/resumable_media/_download.py
google/resumable_media/_helpers.py
google/resumable_media/_upload.py
google/resumable_media/common.py
google/resumable_media/py.typed
google/resumable_media/requests/__init__.py
google/resumable_media/requests/_request_helpers.py
google/resumable_media/requests/download.py
google/resumable_media/requests/upload.py
google_resumable_media-2.7.1.dist-info/LICENSE
google_resumable_media-2.7.1.dist-info/METADATA
google_resumable_media-2.7.1.dist-info/WHEEL
google_resumable_media-2.7.1.dist-info/top_level.txt
google_resumable_media-2.7.1.dist-info/RECORD
