Metadata-Version: 2.1
Name: google-resumable-media
Version: 2.7.1
Summary: Utilities for Google Media Downloads and Resumable Uploads
Home-page: https://github.com/googleapis/google-resumable-media-python
Author: Google Cloud Platform
Author-email: googleapis-publisher@google.com
License: Apache 2.0
Platform: Posix; MacOS X; Windows
Classifier: Development Status :: 5 - Production/Stable
Classifier: Intended Audience :: Developers
Classifier: License :: OSI Approved :: Apache Software License
Classifier: Operating System :: OS Independent
Classifier: Programming Language :: Python :: 3
Classifier: Programming Language :: Python :: 3.7
Classifier: Programming Language :: Python :: 3.8
Classifier: Programming Language :: Python :: 3.9
Classifier: Programming Language :: Python :: 3.10
Classifier: Programming Language :: Python :: 3.11
Classifier: Programming Language :: Python :: 3.12
Classifier: Topic :: Internet
Requires-Python: >= 3.7
License-File: LICENSE
Requires-Dist: google-crc32c<2.0dev,>=1.0
Provides-Extra: requests
Requires-Dist: requests<3.0.0dev,>=2.18.0; extra == "requests"
Provides-Extra: aiohttp
Requires-Dist: aiohttp<4.0.0dev,>=3.6.2; extra == "aiohttp"
Requires-Dist: google-auth<2.0dev,>=1.22.0; extra == "aiohttp"
